<?xml version="1.0"?>
<Question>
<Subject>
Is there any kind of public transport available between noida and greater noida?
</Subject>
<Content>
</Content>
</Question>
<ChosenAnswer>
UP Roadways buses ply frequently between Sector-37 crossing in Noida and Kasna in Greater Noida, passing through Pari Chowk.

Apart from these there are numerous cabs that ferry passengers between Sector-37 crossing and Pari Chowk.
</ChosenAnswer>
<Answers>
<Answer>
Yes bus service is available. it is not frequent.
</Answer>
<Answer>
Hi,

Yes dear, You can find lots of public transport options between Noida to Greater Noida. There are UP Govt. Buses, DTC Buses, Call Center Cabs, Private white line buses most frequently running between Noida and Greater Noida. You can find them From Indian Oil Building, Sector -37, Taj Express Road( Bus Stops) etc. 


Thanks,
</Answer>
</Answers>
